{
    "name": "Eco 08 - Avenue de l'Europe",
    "description": "",
    "arrondissement": "Mont-Saint-Aignan",
    "coordinates": [
        " 1.10022,49.47727"
    ],
    "lines": [],
    "counts": [
        {
            "month": "2022-01-01",
            "count": 2420
        },
        {
            "month": "2022-10-01",
            "count": 4632
        },
        {
            "month": "2022-11-01",
            "count": 2746
        },
        {
            "month": "2022-12-01",
            "count": 1813
        },
        {
            "month": "2022-02-01",
            "count": 2175
        },
        {
            "month": "2022-03-01",
            "count": 4104
        },
        {
            "month": "2022-04-01",
            "count": 3598
        },
        {
            "month": "2022-05-01",
            "count": 4931
        },
        {
            "month": "2022-06-01",
            "count": 4873
        },
        {
            "month": "2022-07-01",
            "count": 4821
        },
        {
            "month": "2022-08-01",
            "count": 5201
        },
        {
            "month": "2022-09-01",
            "count": 4589
        },
        {
            "month": "2023-01-01",
            "count": 2263
        },
        {
            "month": "2023-10-01",
            "count": 5677
        },
        {
            "month": "2023-11-01",
            "count": 2510
        },
        {
            "month": "2023-12-01",
            "count": 1952
        },
        {
            "month": "2023-02-01",
            "count": 2679
        },
        {
            "month": "2023-03-01",
            "count": 2921
        },
        {
            "month": "2023-04-01",
            "count": 3191
        },
        {
            "month": "2023-05-01",
            "count": 4760
        },
        {
            "month": "2023-06-01",
            "count": 5740
        },
        {
            "month": "2023-07-01",
            "count": 4158
        },
        {
            "month": "2023-08-01",
            "count": 3963
        },
        {
            "month": "2023-09-01",
            "count": 5198
        },
        {
            "month": "2024-01-01",
            "count": 1869
        },
        {
            "month": "2024-10-01",
            "count": 3798
        },
        {
            "month": "2024-11-01",
            "count": 2895
        },
        {
            "month": "2024-12-01",
            "count": 2176
        },
        {
            "month": "2024-02-01",
            "count": 1957
        },
        {
            "month": "2024-03-01",
            "count": 2738
        },
        {
            "month": "2024-04-01",
            "count": 2867
        },
        {
            "month": "2024-05-01",
            "count": 4265
        },
        {
            "month": "2024-06-01",
            "count": 4835
        },
        {
            "month": "2024-07-01",
            "count": 4935
        },
        {
            "month": "2024-08-01",
            "count": 4499
        },
        {
            "month": "2024-09-01",
            "count": 4683
        },
        {
            "month": "2025-01-01",
            "count": 1990
        },
        {
            "month": "2025-02-01",
            "count": 2338
        },
        {
            "month": "2025-03-01",
            "count": 4085
        },
        {
            "month": "2025-04-01",
            "count": 4688
        },
        {
            "month": "2025-05-01",
            "count": 4732
        },
        {
            "month": "2025-06-01",
            "count": 5368
        },
        {
            "month": "2025-07-01",
            "count": 2205
        }
    ]
}